CHANGELOG.rst
LICENSE.txt
MANIFEST.in
README.rst
requirements.txt
setup.cfg
setup.py
./pyparticleio/ParticleCloud.py
./pyparticleio/__init__.py
PyParticleIO.egg-info/PKG-INFO
PyParticleIO.egg-info/SOURCES.txt
PyParticleIO.egg-info/dependency_links.txt
PyParticleIO.egg-info/not-zip-safe
PyParticleIO.egg-info/requires.txt
PyParticleIO.egg-info/top_level.txt
pyparticleio/ParticleCloud.py
pyparticleio/__init__.py