Metadata-Version: 2.1
Name: PyParticleIO
Version: 0.1.4
Summary: Python module with a class to interface with the ParticleIO cloud
Home-page: https://github.com/youngsoul/PyParticleIO
Author: Patrick Ryan
Author-email: pat_ryan_99@yahoo.com
Maintainer: Patrick Ryan
Maintainer-email: pat_ryan_99@yahoo.com
License: Public Domain
Keywords: ParticleIO,Photon,Electron,Argon,Boron
Classifier: Development Status :: 4 - Beta
Classifier: Intended Audience :: Developers
Classifier: Natural Language :: English
Classifier: License :: Public Domain
Classifier: Operating System :: OS Independent
Classifier: Programming Language :: Python
Classifier: Programming Language :: Python :: 3
Classifier: Programming Language :: Python :: 3.9
Classifier: Programming Language :: Python :: 3.10
Classifier: Topic :: Software Development :: Libraries :: Python Modules
License-File: LICENSE.txt
